{
  "floorId": "floor-3",
  "source": "cad/campus-map-workspace/sources/floor-3-clean.dxf",
  "generatedBy": "scripts/convert-clean-dxf-to-map.js",
  "coordinateSystem": {
    "rawBounds": {
      "minX": 10.77157808870714,
      "minY": 20.90146920400344,
      "maxX": 54.67810740481195,
      "maxY": 92.41003878928554
    },
    "worldBounds": {
      "minX": -445.153,
      "minY": -725,
      "maxX": 445.153,
      "maxY": 725
    },
    "scale": 20.277289958523227,
    "center": [
      32.72484274675955,
      56.65575399664449
    ],
    "yAxis": "cad-y-inverted-to-world-z"
  },
  "floorShapes": [
    {
      "id": "floor-3-cad-plate-1",
      "label": "Academic floor plate",
      "polygon": [
        [
          444.691,
          -44.937
        ],
        [
          442.387,
          171.413
        ],
        [
          368.517,
          171.413
        ],
        [
          368.517,
          186.327
        ],
        [
          34.359,
          183.226
        ],
        [
          29.604,
          698.643
        ],
        [
          -106.689,
          696.94
        ],
        [
          -106.689,
          725
        ],
        [
          -307.187,
          725
        ],
        [
          -307.187,
          695.129
        ],
        [
          -445.153,
          693.34
        ],
        [
          -441.213,
          146.74
        ],
        [
          -376.796,
          146.74
        ],
        [
          -375.235,
          -197.129
        ],
        [
          -439.211,
          -198.175
        ],
        [
          -434.731,
          -691.718
        ],
        [
          -294.969,
          -688.39
        ],
        [
          -294.969,
          -725
        ],
        [
          -93.658,
          -725
        ],
        [
          -93.658,
          -686.793
        ],
        [
          42.52,
          -686.793
        ],
        [
          36.888,
          -88.373
        ],
        [
          445.153,
          -85.764
        ]
      ]
    }
  ],
  "rooms": [
    {
      "id": "floor-3-3145-1",
      "label": "Room 3145",
      "kind": "Classroom",
      "roomNumber": "3145",
      "plannedRoomNumber": "3145",
      "polygon": [
        [
          37.225,
          -679.089
        ],
        [
          37.225,
          -589.885
        ],
        [
          -95.703,
          -591.716
        ],
        [
          -95.703,
          -680.976
        ]
      ],
      "rawPolygon": [
        [
          34.56063176483247,
          90.14588396528603
        ],
        [
          34.56063176483247,
          85.74667819984072
        ],
        [
          28.00511781397712,
          85.83696110077426
        ],
        [
          28.00511781397712,
          90.23894364034864
        ]
      ],
      "area": 28.8482,
      "worldArea": 11861.43,
      "layer": "rooms",
      "autoClosed": false,
      "height": 0.08,
      "selectable": true,
      "importance": "normal"
    },
    {
      "id": "floor-3-3147-2",
      "label": "Room 3147",
      "kind": "Classroom",
      "roomNumber": "3147",
      "plannedRoomNumber": "3147",
      "polygon": [
        [
          37.01,
          -583.708
        ],
        [
          37.01,
          -494.504
        ],
        [
          -95.918,
          -496.335
        ],
        [
          -95.918,
          -585.595
        ]
      ],
      "rawPolygon": [
        [
          34.55001725319366,
          85.44204216064178
        ],
        [
          34.55001725319366,
          81.04283639519647
        ],
        [
          27.99450330233831,
          81.13311929613002
        ],
        [
          27.99450330233831,
          85.53510183570441
        ]
      ],
      "area": 28.8482,
      "worldArea": 11861.43,
      "layer": "rooms",
      "autoClosed": false,
      "height": 0.08,
      "selectable": true,
      "importance": "normal"
    },
    {
      "id": "floor-3-3149-3",
      "label": "Room 3149",
      "kind": "Classroom",
      "roomNumber": "3149",
      "plannedRoomNumber": "3149",
      "polygon": [
        [
          35.92,
          -488.261
        ],
        [
          34.37,
          -396.353
        ],
        [
          -97.008,
          -398.517
        ],
        [
          -97.008,
          -490.148
        ]
      ],
      "rawPolygon": [
        [
          34.49630651383079,
          80.73494057244064
        ],
        [
          34.41983577461235,
          76.20239240009516
        ],
        [
          27.94079256297544,
          76.30909846970188
        ],
        [
          27.94079256297544,
          80.82800024750325
        ]
      ],
      "area": 29.4992,
      "worldArea": 12129.18,
      "layer": "rooms",
      "autoClosed": false,
      "height": 0.08,
      "selectable": true,
      "importance": "normal"
    },
    {
      "id": "floor-3-3151-4",
      "label": "Room 3151",
      "kind": "Classroom",
      "roomNumber": "3151",
      "plannedRoomNumber": "3151",
      "polygon": [
        [
          35.695,
          -390.981
        ],
        [
          35.695,
          -298.486
        ],
        [
          -97.233,
          -300.316
        ],
        [
          -97.233,
          -392.868
        ]
      ],
      "rawPolygon": [
        [
          34.48518726162388,
          75.93746406131666
        ],
        [
          34.48518726162388,
          71.37594698507768
        ],
        [
          27.92967331076852,
          71.46622988601123
        ],
        [
          27.92967331076852,
          76.03052373637928
        ]
      ],
      "area": 29.9122,
      "worldArea": 12298.96,
      "layer": "rooms",
      "autoClosed": false,
      "height": 0.08,
      "selectable": true,
      "importance": "normal"
    },
    {
      "id": "floor-3-3153-5",
      "label": "Room 3153",
      "kind": "Classroom",
      "roomNumber": "3153",
      "plannedRoomNumber": "3153",
      "polygon": [
        [
          33.095,
          -292.814
        ],
        [
          32.386,
          -200.242
        ],
        [
          -97.911,
          -202.037
        ],
        [
          -97.911,
          -294.701
        ]
      ],
      "rawPolygon": [
        [
          34.3569424669177,
          71.0962308822425
        ],
        [
          34.32200597633285,
          66.53096327064601
        ],
        [
          27.89624015721643,
          66.61945927312858
        ],
        [
          27.89624015721643,
          71.18929055730511
        ]
      ],
      "area": 29.4314,
      "worldArea": 12101.33,
      "layer": "rooms",
      "autoClosed": false,
      "height": 0.08,
      "selectable": true,
      "importance": "normal"
    },
    {
      "id": "floor-3-3155-6",
      "label": "Room 3155",
      "kind": "Support",
      "roomNumber": "3155",
      "plannedRoomNumber": "3155",
      "polygon": [
        [
          33.095,
          -196.043
        ],
        [
          32.386,
          -143.673
        ],
        [
          -97.911,
          -145.468
        ],
        [
          -97.911,
          -197.93
        ]
      ],
      "rawPolygon": [
        [
          34.3569424669177,
          66.32388315923222
        ],
        [
          34.32200597633285,
          63.74118525926849
        ],
        [
          27.89624015721643,
          63.82968126175107
        ],
        [
          27.89624015721643,
          66.41694283429484
        ]
      ],
      "area": 16.6572,
      "worldArea": 6848.88,
      "layer": "rooms",
      "autoClosed": false,
      "height": 0.08,
      "selectable": true,
      "importance": "normal"
    },
    {
      "id": "floor-3-3157-7",
      "label": "Room 3157",
      "kind": "Support",
      "roomNumber": "3157",
      "plannedRoomNumber": "3157",
      "polygon": [
        [
          33.095,
          -138.237
        ],
        [
          32.386,
          -89.101
        ],
        [
          -97.911,
          -90.895
        ],
        [
          -97.911,
          -140.124
        ]
      ],
      "rawPolygon": [
        [
          34.3569424669177,
          63.47308136833603
        ],
        [
          34.32200597633285,
          61.04986902559094
        ],
        [
          27.89624015721643,
          61.13836502807352
        ],
        [
          27.89624015721643,
          63.56614104339865
        ]
      ],
      "area": 15.6296,
      "worldArea": 6426.42,
      "layer": "rooms",
      "autoClosed": false,
      "height": 0.08,
      "selectable": true,
      "importance": "normal"
    },
    {
      "id": "floor-3-3143-8",
      "label": "Room 3143",
      "kind": "Classroom",
      "roomNumber": "3143",
      "plannedRoomNumber": "3143",
      "polygon": [
        [
          -158.012,
          -718.061
        ],
        [
          -158.72,
          -615.454
        ],
        [
          -289.018,
          -617.249
        ],
        [
          -289.018,
          -719.948
        ]
      ],
      "rawPolygon": [
        [
          24.93228416282649,
          92.06784717683556
        ],
        [
          24.89734767224164,
          87.00764634739339
        ],
        [
          18.47158185312521,
          87.09614234987595
        ],
        [
          18.47158185312521,
          92.16090685189818
        ]
      ],
      "area": 32.6203,
      "worldArea": 13412.47,
      "layer": "rooms",
      "autoClosed": false,
      "height": 0.08,
      "selectable": true,
      "importance": "normal"
    },
    {
      "id": "floor-3-3134-9",
      "label": "Room 3134",
      "kind": "Support",
      "roomNumber": "3134",
      "plannedRoomNumber": "3134",
      "polygon": [
        [
          -147.05,
          -331.361
        ],
        [
          -147.58,
          -254.624
        ],
        [
          -261.553,
          -256.309
        ],
        [
          -261.319,
          -333.007
        ]
      ],
      "rawPolygon": [
        [
          25.47287208225764,
          72.9972224096471
        ],
        [
          25.44674405841789,
          69.21283978585461
        ],
        [
          19.82600873730171,
          69.29594194378703
        ],
        [
          19.83755012042824,
          73.07839334207864
        ]
      ],
      "area": 21.2947,
      "worldArea": 8755.71,
      "layer": "rooms",
      "autoClosed": false,
      "height": 0.08,
      "selectable": true,
      "importance": "normal"
    },
    {
      "id": "floor-3-3141-10",
      "label": "Room 3141",
      "kind": "Classroom",
      "roomNumber": "3141",
      "plannedRoomNumber": "3141",
      "polygon": [
        [
          -294.894,
          -684.688
        ],
        [
          -295.602,
          -590.383
        ],
        [
          -428.675,
          -592.178
        ],
        [
          -428.675,
          -686.575
        ],
        [
          -297.669,
          -684.688
        ]
      ],
      "rawPolygon": [
        [
          18.18178606124609,
          90.42198894715355
        ],
        [
          18.14684957066124,
          85.77124441183288
        ],
        [
          11.5842127969103,
          85.85974041431545
        ],
        [
          11.5842127969103,
          90.51504862221618
        ],
        [
          18.04491510661157,
          90.42198894715355
        ]
      ],
      "area": 30.6126,
      "worldArea": 12587,
      "layer": "rooms",
      "autoClosed": false,
      "height": 0.08,
      "selectable": true,
      "importance": "normal"
    },
    {
      "id": "floor-3-3139-11",
      "label": "Room 3139",
      "kind": "Classroom",
      "roomNumber": "3139",
      "plannedRoomNumber": "3139",
      "polygon": [
        [
          -296.303,
          -584.361
        ],
        [
          -430.793,
          -587.815
        ],
        [
          -430.793,
          -496.738
        ],
        [
          -296.947,
          -494.268
        ]
      ],
      "rawPolygon": [
        [
          18.11230859384676,
          85.47424264780508
        ],
        [
          11.47973508964254,
          85.64458043879554
        ],
        [
          11.47973508964254,
          81.15300452711077
        ],
        [
          18.08053596794908,
          81.03120473093452
        ]
      ],
      "area": 29.5611,
      "worldArea": 12154.56,
      "layer": "rooms",
      "autoClosed": false,
      "height": 0.08,
      "selectable": true,
      "importance": "normal"
    },
    {
      "id": "floor-3-3137-12",
      "label": "Room 3137",
      "kind": "Classroom",
      "roomNumber": "3137",
      "plannedRoomNumber": "3137",
      "polygon": [
        [
          -297.304,
          -488.514
        ],
        [
          -297.304,
          -397.005
        ],
        [
          -433.38,
          -400.426
        ],
        [
          -431.28,
          -491.719
        ]
      ],
      "rawPolygon": [
        [
          18.06294484660838,
          80.74741909344293
        ],
        [
          18.06294484660838,
          76.23454581610267
        ],
        [
          11.35217515039599,
          76.40325307921798
        ],
        [
          11.45574929126442,
          80.90550269353405
        ]
      ],
      "area": 30.0242,
      "worldArea": 12344.99,
      "layer": "rooms",
      "autoClosed": false,
      "height": 0.08,
      "selectable": true,
      "importance": "normal"
    },
    {
      "id": "floor-3-3135-13",
      "label": "Room 3135",
      "kind": "Classroom",
      "roomNumber": "3135",
      "plannedRoomNumber": "3135",
      "polygon": [
        [
          -297.537,
          -391.645
        ],
        [
          -297.537,
          -236.918
        ],
        [
          -434.976,
          -239.614
        ],
        [
          -433.397,
          -395.329
        ]
      ],
      "rawPolygon": [
        [
          18.05143634278374,
          75.9701942049991
        ],
        [
          18.05143634278374,
          68.33966384904663
        ],
        [
          11.2734541718102,
          68.47260636315454
        ],
        [
          11.35133022605436,
          76.15189183492824
        ]
      ],
      "area": 51.5929,
      "worldArea": 21213.39,
      "layer": "rooms",
      "autoClosed": false,
      "height": 0.08,
      "selectable": true,
      "importance": "normal"
    },
    {
      "id": "floor-3-space-14-14",
      "label": "space-14",
      "kind": "Named space",
      "roomNumber": "space-14",
      "plannedRoomNumber": "space-14",
      "polygon": [
        [
          -299.418,
          -230.589
        ],
        [
          -299.418,
          -183.048
        ],
        [
          -369.341,
          -183.048
        ],
        [
          -369.341,
          -202.144
        ],
        [
          -434.343,
          -204.247
        ],
        [
          -434.343,
          -233.574
        ]
      ],
      "rawPolygon": [
        [
          17.95868315753277,
          68.0275379832337
        ],
        [
          17.95868315753277,
          65.68301149302047
        ],
        [
          14.51031594143989,
          65.68301149302047
        ],
        [
          14.51031594143989,
          66.62475689848102
        ],
        [
          11.3046726901014,
          66.72845083817953
        ],
        [
          11.3046726901014,
          68.17475662761899
        ]
      ],
      "area": 12.9052,
      "worldArea": 5306.22,
      "layer": "rooms",
      "autoClosed": false,
      "height": 0.09,
      "selectable": true,
      "importance": "normal"
    },
    {
      "id": "floor-3-3133-15",
      "label": "Room 3133",
      "kind": "Classroom",
      "roomNumber": "3133",
      "plannedRoomNumber": "3133",
      "polygon": [
        [
          -147.801,
          -203.148
        ],
        [
          -147.801,
          -88.587
        ],
        [
          -369.305,
          -92.855
        ],
        [
          -369.305,
          -178.61
        ],
        [
          -293.526,
          -178.61
        ],
        [
          -293.526,
          -206.176
        ]
      ],
      "rawPolygon": [
        [
          25.43586954223401,
          66.67425624744165
        ],
        [
          25.43586954223401,
          61.02455221949242
        ],
        [
          14.51210572097659,
          61.23502262349912
        ],
        [
          14.51210572097659,
          65.46414037192497
        ],
        [
          18.24924886877277,
          65.46414037192497
        ],
        [
          18.24924886877277,
          66.82356595371311
        ]
      ],
      "area": 56.5806,
      "worldArea": 23264.19,
      "layer": "rooms",
      "autoClosed": false,
      "height": 0.08,
      "selectable": true,
      "importance": "normal"
    },
    {
      "id": "floor-3-3142-16",
      "label": "Room 3142",
      "kind": "Classroom",
      "roomNumber": "3142",
      "plannedRoomNumber": "3142",
      "polygon": [
        [
          -207.793,
          -507.644
        ],
        [
          -207.793,
          -445.429
        ],
        [
          -260.34,
          -445.429
        ],
        [
          -260.34,
          -508.529
        ]
      ],
      "rawPolygon": [
        [
          22.47728528000753,
          81.69084464232122
        ],
        [
          22.47728528000753,
          78.62265129125443
        ],
        [
          19.8858547523549,
          78.62265129125443
        ],
        [
          19.8858547523549,
          81.73449995886382
        ]
      ],
      "area": 8.0076,
      "worldArea": 3292.46,
      "layer": "rooms",
      "autoClosed": false,
      "height": 0.09,
      "selectable": true,
      "importance": "normal"
    },
    {
      "id": "floor-3-3140-17",
      "label": "Room 3140",
      "kind": "Classroom",
      "roomNumber": "3140",
      "plannedRoomNumber": "3140",
      "polygon": [
        [
          -207.981,
          -439.19
        ],
        [
          -207.981,
          -415.689
        ],
        [
          -260.317,
          -415.689
        ],
        [
          -260.317,
          -440.595
        ]
      ],
      "rawPolygon": [
        [
          22.46798303400696,
          78.31495689912035
        ],
        [
          22.46798303400696,
          77.15595860256988
        ],
        [
          19.88700425636359,
          77.15595860256988
        ],
        [
          19.88700425636359,
          78.38424055171862
        ]
      ],
      "area": 3.0808,
      "worldArea": 1266.71,
      "layer": "rooms",
      "autoClosed": false,
      "height": 0.09,
      "selectable": true,
      "importance": "normal"
    },
    {
      "id": "floor-3-3138-18",
      "label": "Room 3138",
      "kind": "Classroom",
      "roomNumber": "3138",
      "plannedRoomNumber": "3138",
      "polygon": [
        [
          -208.215,
          -409.983
        ],
        [
          -208.215,
          -378.855
        ],
        [
          -260.636,
          -379.636
        ],
        [
          -260.636,
          -410.493
        ],
        [
          -208.215,
          -410.493
        ]
      ],
      "rawPolygon": [
        [
          22.45648230923078,
          76.87455578331767
        ],
        [
          22.45648230923078,
          75.33943944477366
        ],
        [
          19.87126873727742,
          75.37799199358633
        ],
        [
          19.87126873727742,
          76.89973588323186
        ],
        [
          22.45648230923078,
          76.89973588323186
        ]
      ],
      "area": 3.9839,
      "worldArea": 1638.03,
      "layer": "rooms",
      "autoClosed": false,
      "height": 0.09,
      "selectable": true,
      "importance": "normal"
    },
    {
      "id": "floor-3-space-19-19",
      "label": "space-19",
      "kind": "Named space",
      "roomNumber": "space-19",
      "plannedRoomNumber": "space-19",
      "polygon": [
        [
          -208.228,
          -373.196
        ],
        [
          -208.228,
          -337.764
        ],
        [
          -261.371,
          -339.075
        ],
        [
          -261.371,
          -373.252
        ]
      ],
      "rawPolygon": [
        [
          22.45581660219816,
          75.06039230363496
        ],
        [
          22.45581660219816,
          73.31299819832641
        ],
        [
          19.83500161652847,
          73.3776459781728
        ],
        [
          19.83500161652847,
          75.06314533015393
        ]
      ],
      "area": 4.4985,
      "worldArea": 1849.62,
      "layer": "rooms",
      "autoClosed": false,
      "height": 0.09,
      "selectable": true,
      "importance": "normal"
    },
    {
      "id": "floor-3-3134a-20",
      "label": "Room 3134A",
      "kind": "Classroom",
      "roomNumber": "3134A",
      "plannedRoomNumber": "3134A",
      "polygon": [
        [
          -146.692,
          -372.225
        ],
        [
          -146.692,
          -337.655
        ],
        [
          -202.735,
          -337.655
        ],
        [
          -202.735,
          -373.365
        ]
      ],
      "rawPolygon": [
        [
          25.49052214485022,
          75.01250694403528
        ],
        [
          25.49052214485022,
          73.30761936462856
        ],
        [
          22.72670221838879,
          73.30761936462856
        ],
        [
          22.72670221838879,
          75.06873662014969
        ]
      ],
      "area": 4.7897,
      "worldArea": 1969.35,
      "layer": "rooms",
      "autoClosed": false,
      "height": 0.09,
      "selectable": true,
      "importance": "normal"
    },
    {
      "id": "floor-3-space-21-21",
      "label": "space-21",
      "kind": "Named space",
      "roomNumber": "space-21",
      "plannedRoomNumber": "space-21",
      "polygon": [
        [
          -146.007,
          -462.109
        ],
        [
          -146.007,
          -506.894
        ],
        [
          -201.983,
          -506.894
        ],
        [
          -201.983,
          -444.903
        ],
        [
          -159.591,
          -444.903
        ]
      ],
      "rawPolygon": [
        [
          25.52430445800099,
          79.44522906868463
        ],
        [
          25.52430445800099,
          81.65387342990554
        ],
        [
          22.76380319329501,
          81.65387342990554
        ],
        [
          22.76380319329501,
          78.59669557743032
        ],
        [
          24.8544030222814,
          78.59669557743032
        ]
      ],
      "area": 8.1551,
      "worldArea": 3353.15,
      "layer": "rooms",
      "autoClosed": false,
      "height": 0.09,
      "selectable": true,
      "importance": "normal"
    },
    {
      "id": "floor-3-space-22-22",
      "label": "space-22",
      "kind": "Named space",
      "roomNumber": "space-22",
      "plannedRoomNumber": "space-22",
      "polygon": [
        [
          -146.133,
          -422.261
        ],
        [
          -146.133,
          -378.152
        ],
        [
          -202.516,
          -378.152
        ],
        [
          -202.516,
          -440.071
        ],
        [
          -159.128,
          -440.071
        ]
      ],
      "rawPolygon": [
        [
          25.51813447578672,
          77.48006428957208
        ],
        [
          25.51813447578672,
          75.30477302273545
        ],
        [
          22.73752855950136,
          75.30477302273545
        ],
        [
          22.73752855950136,
          78.35840060749398
        ],
        [
          24.87722286097137,
          78.35840060749398
        ]
      ],
      "area": 8.2095,
      "worldArea": 3375.46,
      "layer": "rooms",
      "autoClosed": false,
      "height": 0.09,
      "selectable": true,
      "importance": "normal"
    },
    {
      "id": "floor-3-space-23-23",
      "label": "space-23",
      "kind": "Named space",
      "roomNumber": "space-23",
      "plannedRoomNumber": "space-23",
      "polygon": [
        [
          -145.774,
          -540.702
        ],
        [
          -259.921,
          -542.186
        ],
        [
          -259.921,
          -514.147
        ],
        [
          -145.596,
          -514.147
        ]
      ],
      "rawPolygon": [
        [
          25.53579530936949,
          83.32113461729524
        ],
        [
          19.90652847124936,
          83.3943268720847
        ],
        [
          19.90652847124936,
          82.01154466758993
        ],
        [
          25.54460508176301,
          82.01154466758993
        ]
      ],
      "area": 7.5838,
      "worldArea": 3118.23,
      "layer": "rooms",
      "autoClosed": false,
      "height": 0.09,
      "selectable": true,
      "importance": "normal"
    },
    {
      "id": "floor-3-3101-24",
      "label": "Room 3101",
      "kind": "Classroom",
      "roomNumber": "3101",
      "plannedRoomNumber": "3101",
      "polygon": [
        [
          363.162,
          49.789
        ],
        [
          363.162,
          180.601
        ],
        [
          256.109,
          180.601
        ],
        [
          256.109,
          48.787
        ]
      ],
      "rawPolygon": [
        [
          50.63462293467055,
          54.2003282873761
        ],
        [
          50.63462293467055,
          47.74918100689686
        ],
        [
          45.35517332402391,
          47.74918100689686
        ],
        [
          45.35517332402391,
          54.24977590047175
        ]
      ],
      "area": 34.189,
      "worldArea": 14057.45,
      "layer": "rooms",
      "autoClosed": false,
      "height": 0.08,
      "selectable": true,
      "importance": "normal"
    },
    {
      "id": "floor-3-3103-25",
      "label": "Room 3103",
      "kind": "Classroom",
      "roomNumber": "3103",
      "plannedRoomNumber": "3103",
      "polygon": [
        [
          251.306,
          49.025
        ],
        [
          251.306,
          179.963
        ],
        [
          144.049,
          178.192
        ],
        [
          144.049,
          46.628
        ]
      ],
      "rawPolygon": [
        [
          45.11830698276824,
          54.2380034468068
        ],
        [
          45.11830698276824,
          47.78063429246955
        ],
        [
          39.82880504633192,
          47.86800599083797
        ],
        [
          39.82880504633192,
          54.35622244262475
        ]
      ],
      "area": 34.2379,
      "worldArea": 14077.59,
      "layer": "rooms",
      "autoClosed": false,
      "height": 0.08,
      "selectable": true,
      "importance": "normal"
    },
    {
      "id": "floor-3-3105-26",
      "label": "Room 3105",
      "kind": "Classroom",
      "roomNumber": "3105",
      "plannedRoomNumber": "3105",
      "polygon": [
        [
          138.988,
          47.249
        ],
        [
          138.988,
          178.763
        ],
        [
          34.52,
          177.335
        ],
        [
          35.542,
          46.035
        ]
      ],
      "rawPolygon": [
        [
          39.57921188258337,
          54.3255943865046
        ],
        [
          39.57921188258337,
          47.8398209701115
        ],
        [
          34.4272366416501,
          47.91024153954547
        ],
        [
          34.47766492175233,
          54.38546974484075
        ]
      ],
      "area": 33.2256,
      "worldArea": 13661.35,
      "layer": "rooms",
      "autoClosed": false,
      "height": 0.08,
      "selectable": true,
      "importance": "normal"
    },
    {
      "id": "floor-3-space-27-27",
      "label": "space-27",
      "kind": "Named space",
      "roomNumber": "space-27",
      "plannedRoomNumber": "space-27",
      "polygon": [
        [
          29.081,
          128.818
        ],
        [
          29.081,
          149.965
        ],
        [
          -17.094,
          149.965
        ],
        [
          -17.094,
          95.222
        ],
        [
          1.646,
          95.222
        ],
        [
          1.646,
          127.918
        ]
      ],
      "rawPolygon": [
        [
          34.15902971088107,
          50.30295150667857
        ],
        [
          34.15902971088107,
          49.26005103548273
        ],
        [
          31.88184371962612,
          49.26005103548273
        ],
        [
          31.88184371962612,
          51.95975780870191
        ],
        [
          32.80602639257478,
          51.95975780870191
        ],
        [
          32.80602639257478,
          50.34733027720166
        ]
      ],
      "area": 3.9361,
      "worldArea": 1618.4,
      "layer": "rooms",
      "autoClosed": false,
      "height": 0.09,
      "selectable": true,
      "importance": "normal"
    },
    {
      "id": "floor-3-3113-28",
      "label": "Room 3113",
      "kind": "Classroom",
      "roomNumber": "3113",
      "plannedRoomNumber": "3113",
      "polygon": [
        [
          28.667,
          156.257
        ],
        [
          28.667,
          259.527
        ],
        [
          -102.284,
          257.921
        ],
        [
          -102.284,
          154.243
        ]
      ],
      "rawPolygon": [
        [
          34.13859624490669,
          48.94972277894488
        ],
        [
          34.13859624490669,
          43.8568539858709
        ],
        [
          27.68056843190862,
          43.93605014538241
        ],
        [
          27.68056843190862,
          49.04904546211882
        ]
      ],
      "area": 32.9549,
      "worldArea": 13550.02,
      "layer": "rooms",
      "autoClosed": false,
      "height": 0.08,
      "selectable": true,
      "importance": "normal"
    },
    {
      "id": "floor-3-space-29-29",
      "label": "space-29",
      "kind": "Named space",
      "roomNumber": "space-29",
      "plannedRoomNumber": "space-29",
      "polygon": [
        [
          -22.199,
          94.111
        ],
        [
          -22.199,
          149.861
        ],
        [
          -100.842,
          148.369
        ],
        [
          -100.842,
          94.247
        ]
      ],
      "rawPolygon": [
        [
          31.63007750860658,
          52.01455202659595
        ],
        [
          31.63007750860658,
          49.26515125882586
        ],
        [
          27.75171620761363,
          49.33873619731166
        ],
        [
          27.75171620761363,
          52.00786283369544
        ]
      ],
      "area": 10.5075,
      "worldArea": 4320.33,
      "layer": "rooms",
      "autoClosed": false,
      "height": 0.09,
      "selectable": true,
      "importance": "normal"
    },
    {
      "id": "floor-3-3115-30",
      "label": "Room 3115",
      "kind": "Classroom",
      "roomNumber": "3115",
      "plannedRoomNumber": "3115",
      "polygon": [
        [
          28.366,
          265.595
        ],
        [
          26.771,
          399.838
        ],
        [
          -103.922,
          397.84
        ],
        [
          -101.911,
          264.485
        ]
      ],
      "rawPolygon": [
        [
          34.12372719214254,
          43.55761501514187
        ],
        [
          34.04506455642028,
          36.9372244540612
        ],
        [
          27.59977463609946,
          37.0357575291978
        ],
        [
          27.69895181941669,
          43.61232187575573
        ]
      ],
      "area": 42.4682,
      "worldArea": 17461.56,
      "layer": "rooms",
      "autoClosed": false,
      "height": 0.08,
      "selectable": true,
      "importance": "normal"
    },
    {
      "id": "floor-3-3117-31",
      "label": "Room 3117",
      "kind": "Classroom",
      "roomNumber": "3117",
      "plannedRoomNumber": "3117",
      "polygon": [
        [
          26.775,
          448.762
        ],
        [
          25.426,
          582.519
        ],
        [
          -105.713,
          580.068
        ],
        [
          -104.587,
          447.495
        ]
      ],
      "rawPolygon": [
        [
          34.04529673109773,
          34.52447786493264
        ],
        [
          33.97875056175755,
          27.92810504306243
        ],
        [
          27.51145550847703,
          28.04897444179836
        ],
        [
          27.56701975573522,
          34.58696037161114
        ]
      ],
      "area": 42.5135,
      "worldArea": 17480.27,
      "layer": "rooms",
      "autoClosed": false,
      "height": 0.08,
      "selectable": true,
      "importance": "normal"
    },
    {
      "id": "floor-3-3119-32",
      "label": "Room 3119",
      "kind": "Classroom",
      "roomNumber": "3119",
      "plannedRoomNumber": "3119",
      "polygon": [
        [
          25.627,
          587.566
        ],
        [
          25.627,
          693.362
        ],
        [
          -106.984,
          691.493
        ],
        [
          -106.984,
          586.348
        ]
      ],
      "rawPolygon": [
        [
          33.98867243888826,
          27.67920846145417
        ],
        [
          33.98867243888826,
          22.46173171730428
        ],
        [
          27.44876924314937,
          22.5538851666012
        ],
        [
          27.44876924314937,
          27.73928991512122
        ]
      ],
      "area": 34.0169,
      "worldArea": 13986.55,
      "layer": "rooms",
      "autoClosed": false,
      "height": 0.08,
      "selectable": true,
      "importance": "normal"
    },
    {
      "id": "floor-3-3121-33",
      "label": "Room 3121",
      "kind": "Classroom",
      "roomNumber": "3121",
      "plannedRoomNumber": "3121",
      "polygon": [
        [
          -168.261,
          615.876
        ],
        [
          -168.261,
          719.972
        ],
        [
          -302.327,
          719.972
        ],
        [
          -302.327,
          614.5
        ]
      ],
      "rawPolygon": [
        [
          24.42682163918408,
          26.28306101715685
        ],
        [
          24.42682163918408,
          21.14941503307697
        ],
        [
          17.81520638753186,
          21.14941503307697
        ],
        [
          17.81520638753186,
          26.35089521740733
        ]
      ],
      "area": 34.1659,
      "worldArea": 14047.97,
      "layer": "rooms",
      "autoClosed": false,
      "height": 0.08,
      "selectable": true,
      "importance": "normal"
    },
    {
      "id": "floor-3-3116-34",
      "label": "Room 3116",
      "kind": "Classroom",
      "roomNumber": "3116",
      "plannedRoomNumber": "3116",
      "polygon": [
        [
          -151.397,
          206.419
        ],
        [
          -151.397,
          283.562
        ],
        [
          -265.379,
          283.562
        ],
        [
          -265.379,
          206.422
        ]
      ],
      "rawPolygon": [
        [
          25.25849437174358,
          46.47592617290692
        ],
        [
          25.25849437174358,
          42.67156157205175
        ],
        [
          19.63732731824689,
          42.67156157205175
        ],
        [
          19.63732731824689,
          46.47578156692371
        ]
      ],
      "area": 21.3846,
      "worldArea": 8792.74,
      "layer": "rooms",
      "autoClosed": false,
      "height": 0.09,
      "selectable": true,
      "importance": "normal"
    },
    {
      "id": "floor-3-3116a-35",
      "label": "Room 3116A",
      "kind": "Classroom",
      "roomNumber": "3116A",
      "plannedRoomNumber": "3116A",
      "polygon": [
        [
          -152.21,
          289.251
        ],
        [
          -152.21,
          323.848
        ],
        [
          -207.394,
          323.848
        ],
        [
          -207.394,
          289.928
        ]
      ],
      "rawPolygon": [
        [
          25.21843017775823,
          42.39097550096275
        ],
        [
          25.21843017775823,
          40.68477247357978
        ],
        [
          22.49694862018327,
          40.68477247357978
        ],
        [
          22.49694862018327,
          42.35758424077643
        ]
      ],
      "area": 4.598,
      "worldArea": 1890.52,
      "layer": "rooms",
      "autoClosed": false,
      "height": 0.09,
      "selectable": true,
      "importance": "normal"
    },
    {
      "id": "floor-3-space-36-36",
      "label": "space-36",
      "kind": "Named space",
      "roomNumber": "space-36",
      "plannedRoomNumber": "space-36",
      "polygon": [
        [
          -213.634,
          289.653
        ],
        [
          -213.634,
          323.814
        ],
        [
          -265.989,
          323.814
        ],
        [
          -265.989,
          289.887
        ],
        [
          -213.634,
          289.887
        ]
      ],
      "rawPolygon": [
        [
          22.1891906134338,
          42.37116872190836
        ],
        [
          22.1891906134338,
          40.68645261699755
        ],
        [
          19.60723825795486,
          40.68645261699755
        ],
        [
          19.60723825795486,
          42.35959515447836
        ],
        [
          22.1891906134338,
          42.35959515447836
        ]
      ],
      "area": 4.32,
      "worldArea": 1776.25,
      "layer": "rooms",
      "autoClosed": false,
      "height": 0.09,
      "selectable": true,
      "importance": "normal"
    },
    {
      "id": "floor-3-3130-37",
      "label": "Room 3130",
      "kind": "Classroom",
      "roomNumber": "3130",
      "plannedRoomNumber": "3130",
      "polygon": [
        [
          -214.551,
          329.71
        ],
        [
          -214.551,
          363.518
        ],
        [
          -267.062,
          363.518
        ],
        [
          -267.062,
          329.145
        ]
      ],
      "rawPolygon": [
        [
          22.14397698855475,
          40.39569027089691
        ],
        [
          22.14397698855475,
          38.72841424125086
        ],
        [
          19.55436346710847,
          38.72841424125086
        ],
        [
          19.55436346710847,
          40.42355130637069
        ]
      ],
      "area": 4.3537,
      "worldArea": 1790.13,
      "layer": "rooms",
      "autoClosed": false,
      "height": 0.09,
      "selectable": true,
      "importance": "normal"
    },
    {
      "id": "floor-3-3128-38",
      "label": "Room 3128",
      "kind": "Classroom",
      "roomNumber": "3128",
      "plannedRoomNumber": "3128",
      "polygon": [
        [
          -214.58,
          370.289
        ],
        [
          -214.58,
          405.962
        ],
        [
          -266.985,
          405.962
        ],
        [
          -266.985,
          370.289
        ]
      ],
      "rawPolygon": [
        [
          22.14258304290756,
          38.39450630409682
        ],
        [
          22.14258304290756,
          36.63523754558679
        ],
        [
          19.5581464782188,
          36.63523754558679
        ],
        [
          19.5581464782188,
          38.39450630409682
        ]
      ],
      "area": 4.5467,
      "worldArea": 1869.44,
      "layer": "rooms",
      "autoClosed": false,
      "height": 0.09,
      "selectable": true,
      "importance": "normal"
    },
    {
      "id": "floor-3-3126-39",
      "label": "Room 3126",
      "kind": "Classroom",
      "roomNumber": "3126",
      "plannedRoomNumber": "3126",
      "polygon": [
        [
          -215.162,
          412.055
        ],
        [
          -215.162,
          481.383
        ],
        [
          -268.274,
          481.383
        ],
        [
          -268.274,
          412.308
        ],
        [
          -216.431,
          412.308
        ]
      ],
      "rawPolygon": [
        [
          22.11387027580657,
          36.33475988255002
        ],
        [
          22.11387027580657,
          32.91574987184141
        ],
        [
          19.49455335535592,
          32.91574987184141
        ],
        [
          19.49455335535592,
          36.32228263374111
        ],
        [
          22.05126509209952,
          36.32228263374111
        ]
      ],
      "area": 8.9232,
      "worldArea": 3668.87,
      "layer": "rooms",
      "autoClosed": false,
      "height": 0.09,
      "selectable": true,
      "importance": "normal"
    },
    {
      "id": "floor-3-space-40-40",
      "label": "space-40",
      "kind": "Named space",
      "roomNumber": "space-40",
      "plannedRoomNumber": "space-40",
      "polygon": [
        [
          -154.66,
          486.607
        ],
        [
          -154.66,
          516.24
        ],
        [
          -268.202,
          516.24
        ],
        [
          -268.202,
          487.72
        ]
      ],
      "rawPolygon": [
        [
          25.09761018562354,
          32.65811544189317
        ],
        [
          25.09761018562354,
          31.19672228685117
        ],
        [
          19.49814877172042,
          31.19672228685117
        ],
        [
          19.49814877172042,
          32.60322072072047
        ]
      ],
      "area": 8.0293,
      "worldArea": 3301.4,
      "layer": "rooms",
      "autoClosed": false,
      "height": 0.09,
      "selectable": true,
      "importance": "normal"
    },
    {
      "id": "floor-3-space-41-41",
      "label": "space-41",
      "kind": "Named space",
      "roomNumber": "space-41",
      "plannedRoomNumber": "space-41",
      "polygon": [
        [
          -153.441,
          388.616
        ],
        [
          -153.441,
          329.369
        ],
        [
          -208.309,
          329.369
        ],
        [
          -208.309,
          406.547
        ],
        [
          -166.646,
          406.547
        ]
      ],
      "rawPolygon": [
        [
          25.15773116012077,
          37.4906726860395
        ],
        [
          25.15773116012077,
          40.4125243580385
        ],
        [
          22.45184569714785,
          40.4125243580385
        ],
        [
          22.45184569714785,
          36.60637911048693
        ],
        [
          24.50647341083886,
          36.60637911048693
        ]
      ],
      "area": 10.011,
      "worldArea": 4116.21,
      "layer": "rooms",
      "autoClosed": false,
      "height": 0.09,
      "selectable": true,
      "importance": "normal"
    },
    {
      "id": "floor-3-space-42-42",
      "label": "space-42",
      "kind": "Named space",
      "roomNumber": "space-42",
      "plannedRoomNumber": "space-42",
      "polygon": [
        [
          -153.678,
          428.744
        ],
        [
          -154.781,
          480.553
        ],
        [
          -209.999,
          481.322
        ],
        [
          -209.999,
          411.424
        ],
        [
          -166.735,
          411.424
        ]
      ],
      "rawPolygon": [
        [
          25.14604343898712,
          35.51170672885247
        ],
        [
          25.09160146906797,
          32.95669796082747
        ],
        [
          22.36846447013952,
          32.91875182420243
        ],
        [
          22.36846447013952,
          36.36586670745328
        ],
        [
          24.50208752347201,
          36.36586670745328
        ]
      ],
      "area": 9.1763,
      "worldArea": 3773,
      "layer": "rooms",
      "autoClosed": false,
      "height": 0.09,
      "selectable": true,
      "importance": "normal"
    },
    {
      "id": "floor-3-3131-43",
      "label": "Room 3131",
      "kind": "Classroom",
      "roomNumber": "3131",
      "plannedRoomNumber": "3131",
      "polygon": [
        [
          -150.153,
          45.334
        ],
        [
          -153.08,
          160.643
        ],
        [
          -295.676,
          160.643
        ],
        [
          -295.676,
          132.461
        ],
        [
          -351.586,
          132.461
        ],
        [
          -370.981,
          132.461
        ],
        [
          -370.981,
          44.454
        ]
      ],
      "rawPolygon": [
        [
          25.3198501205885,
          54.42004372082518
        ],
        [
          25.17553470932356,
          48.7334562618049
        ],
        [
          18.14319949451968,
          48.7334562618049
        ],
        [
          18.14319949451968,
          50.12325418883968
        ],
        [
          15.38593850269607,
          50.12325418883968
        ],
        [
          14.42945722049541,
          50.12325418883968
        ],
        [
          14.42945722049541,
          54.46343738959171
        ]
      ],
      "area": 56.5938,
      "worldArea": 23269.62,
      "layer": "rooms",
      "autoClosed": false,
      "height": 0.08,
      "selectable": true,
      "importance": "normal"
    },
    {
      "id": "floor-3-3129-44",
      "label": "Room 3129",
      "kind": "Classroom",
      "roomNumber": "3129",
      "plannedRoomNumber": "3129",
      "polygon": [
        [
          -301.773,
          186.536
        ],
        [
          -304.541,
          347.196
        ],
        [
          -437.788,
          347.196
        ],
        [
          -437.788,
          188.956
        ],
        [
          -301.815,
          188.956
        ]
      ],
      "rawPolygon": [
        [
          17.84250426539362,
          47.45648238244046
        ],
        [
          17.70604539389031,
          39.53333142989352
        ],
        [
          11.13479203442454,
          39.53333142989352
        ],
        [
          11.13479203442454,
          47.33713155856041
        ],
        [
          17.84044870961319,
          47.33713155856041
        ]
      ],
      "area": 51.8052,
      "worldArea": 21300.71,
      "layer": "rooms",
      "autoClosed": false,
      "height": 0.08,
      "selectable": true,
      "importance": "normal"
    },
    {
      "id": "floor-3-3127-45",
      "label": "Room 3127",
      "kind": "Classroom",
      "roomNumber": "3127",
      "plannedRoomNumber": "3127",
      "polygon": [
        [
          -303.913,
          352.279
        ],
        [
          -303.913,
          463.355
        ],
        [
          -438.746,
          463.355
        ],
        [
          -437.356,
          350.887
        ]
      ],
      "rawPolygon": [
        [
          17.73700121969852,
          39.28268049358579
        ],
        [
          17.73700121969852,
          33.80483367961183
        ],
        [
          11.08751456814727,
          33.80483367961183
        ],
        [
          11.15606144891539,
          39.35132889761268
        ]
      ],
      "area": 36.4654,
      "worldArea": 14993.36,
      "layer": "rooms",
      "autoClosed": false,
      "height": 0.08,
      "selectable": true,
      "importance": "normal"
    },
    {
      "id": "floor-3-3125-46",
      "label": "Room 3125",
      "kind": "Classroom",
      "roomNumber": "3125",
      "plannedRoomNumber": "3125",
      "polygon": [
        [
          -305.509,
          469.347
        ],
        [
          -305.509,
          580.878
        ],
        [
          -439.523,
          579.541
        ],
        [
          -438.261,
          468.108
        ]
      ],
      "rawPolygon": [
        [
          17.65828861854955,
          33.50930654516137
        ],
        [
          17.65828861854955,
          28.00901399895566
        ],
        [
          11.04919856570871,
          28.07496959361787
        ],
        [
          11.11144890512781,
          33.57039896851746
        ]
      ],
      "area": 36.1667,
      "worldArea": 14870.62,
      "layer": "rooms",
      "autoClosed": false,
      "height": 0.08,
      "selectable": true,
      "importance": "normal"
    },
    {
      "id": "floor-3-3123-47",
      "label": "Room 3123",
      "kind": "Classroom",
      "roomNumber": "3123",
      "plannedRoomNumber": "3123",
      "polygon": [
        [
          -306.672,
          587
        ],
        [
          -306.672,
          690.299
        ],
        [
          -439.512,
          688.336
        ],
        [
          -439.512,
          583.398
        ]
      ],
      "rawPolygon": [
        [
          17.60091664010435,
          27.70712759375991
        ],
        [
          17.60091664010435,
          22.61277330285846
        ],
        [
          11.04975327170354,
          22.70961436077223
        ],
        [
          11.04975327170354,
          27.88475802138725
        ]
      ],
      "area": 33.6386,
      "worldArea": 13831.1,
      "layer": "rooms",
      "autoClosed": false,
      "height": 0.08,
      "selectable": true,
      "importance": "normal"
    }
  ],
  "hallways": [
    {
      "id": "floor-3-hallway-1",
      "label": "Hallway 1",
      "kind": "Hallway",
      "polygon": [
        [
          439.869,
          -78.94
        ],
        [
          439.869,
          45.305
        ],
        [
          -267.688,
          38.968
        ],
        [
          -267.688,
          -86.248
        ]
      ],
      "rawPolygon": [
        [
          54.41751017861268,
          60.54880065507074
        ],
        [
          54.41751017861268,
          54.42147578652983
        ],
        [
          19.52347376321225,
          54.73401299487562
        ],
        [
          19.52347376321225,
          60.90919693101928
        ]
      ],
      "area": 214.6421,
      "height": 0.045,
      "selectable": true,
      "autoClosed": false
    },
    {
      "id": "floor-3-hallway-2",
      "label": "Hallway 2",
      "kind": "Hallway",
      "polygon": [
        [
          -145.574,
          165.668
        ],
        [
          -145.574,
          202.197
        ],
        [
          -296.32,
          202.197
        ],
        [
          -296.32,
          166.438
        ],
        [
          -145.574,
          166.438
        ]
      ],
      "rawPolygon": [
        [
          25.54567589770448,
          48.48560966381662
        ],
        [
          25.54567589770448,
          46.68416133310874
        ],
        [
          18.11146037836925,
          46.68416133310874
        ],
        [
          18.11146037836925,
          48.44766861596519
        ],
        [
          25.54567589770448,
          48.44766861596519
        ]
      ],
      "area": 13.1103,
      "height": 0.045,
      "selectable": true,
      "autoClosed": false
    },
    {
      "id": "floor-3-hallway-3",
      "label": "Hallway 3",
      "kind": "Hallway",
      "polygon": [
        [
          -269.436,
          202.197
        ],
        [
          -275.655,
          610.317
        ],
        [
          -300.429,
          610.317
        ],
        [
          -296.32,
          202.197
        ]
      ],
      "rawPolygon": [
        [
          19.43724540446351,
          46.68416133310874
        ],
        [
          19.13056868545153,
          26.55722760034627
        ],
        [
          17.90883411734747,
          26.55722760034627
        ],
        [
          18.11146037836925,
          46.68416133310874
        ]
      ],
      "area": 25.6369,
      "height": 0.045,
      "selectable": true,
      "autoClosed": false
    },
    {
      "id": "floor-3-hallway-4",
      "label": "Hallway 4",
      "kind": "Hallway",
      "polygon": [
        [
          -149.736,
          522.036
        ],
        [
          -162.414,
          609.969
        ],
        [
          -275.65,
          609.969
        ],
        [
          -275.655,
          610.317
        ],
        [
          -274.329,
          523.304
        ]
      ],
      "rawPolygon": [
        [
          25.34042450701788,
          30.91091725436832
        ],
        [
          24.71521280718223,
          26.57435938074361
        ],
        [
          19.13082972462783,
          26.57435938074361
        ],
        [
          19.13056868545153,
          26.55722760034627
        ],
        [
          19.19595308003777,
          30.84835012583111
        ]
      ],
      "area": 25.2372,
      "height": 0.045,
      "selectable": true,
      "autoClosed": false
    },
    {
      "id": "floor-3-hallway-5",
      "label": "Hallway 5",
      "kind": "Hallway",
      "polygon": [
        [
          -162.414,
          609.969
        ],
        [
          -113.276,
          609.969
        ],
        [
          -105.204,
          40.423
        ],
        [
          -141.276,
          40.1
        ],
        [
          -149.736,
          522.036
        ]
      ],
      "rawPolygon": [
        [
          24.71521280718223,
          26.57435938074361
        ],
        [
          27.13847347143329,
          26.57435938074361
        ],
        [
          27.53655999386411,
          54.66224177382947
        ],
        [
          25.75764359916337,
          54.67817508567858
        ],
        [
          25.34042450701788,
          30.91091725436832
        ]
      ],
      "area": 52.5125,
      "height": 0.045,
      "selectable": true,
      "autoClosed": false
    },
    {
      "id": "floor-3-hallway-6",
      "label": "Hallway 6",
      "kind": "Hallway",
      "polygon": [
        [
          -104.87,
          -84.567
        ],
        [
          -100.478,
          -615.162
        ],
        [
          -140.517,
          -614.085
        ],
        [
          -140.3,
          -545.579
        ],
        [
          -140.3,
          -84.933
        ]
      ],
      "rawPolygon": [
        [
          27.55305965486548,
          60.82626491311482
        ],
        [
          27.76964978758208,
          86.99323196746147
        ],
        [
          25.79505094890166,
          86.94011434768176
        ],
        [
          25.80576150186967,
          83.56165677381163
        ],
        [
          25.80576150186967,
          60.84431154262524
        ]
      ],
      "area": 48.5057,
      "height": 0.045,
      "selectable": true,
      "autoClosed": false
    },
    {
      "id": "floor-3-hallway-7",
      "label": "Hallway 7",
      "kind": "Hallway",
      "polygon": [
        [
          -261.22,
          -615.267
        ],
        [
          -259.237,
          -615.29
        ],
        [
          -259.921,
          -542.186
        ],
        [
          -140.3,
          -545.579
        ],
        [
          -150.712,
          -610.963
        ]
      ],
      "rawPolygon": [
        [
          19.842445759336,
          86.99840861420996
        ],
        [
          19.94023329310959,
          86.99954918637565
        ],
        [
          19.90652847124936,
          83.3943268720847
        ],
        [
          25.80576150186967,
          83.56165677381163
        ],
        [
          25.29230002203976,
          86.78618149059243
        ]
      ],
      "area": 19.1919,
      "height": 0.045,
      "selectable": true,
      "autoClosed": false
    },
    {
      "id": "floor-3-hallway-8",
      "label": "Hallway 8",
      "kind": "Hallway",
      "polygon": [
        [
          -262.894,
          -609.548
        ],
        [
          -269.006,
          -211.438
        ],
        [
          -294.14,
          -213.034
        ],
        [
          -291.251,
          -611.197
        ]
      ],
      "rawPolygon": [
        [
          19.75990391341069,
          86.71639207164834
        ],
        [
          19.45846631545296,
          67.08307969481535
        ],
        [
          18.21895695483214,
          67.16177432862575
        ],
        [
          18.36144458890055,
          86.79772155692953
        ]
      ],
      "area": 25.9155,
      "height": 0.045,
      "selectable": true,
      "autoClosed": false
    }
  ],
  "outerOutlines": [
    {
      "id": "floor-3-outer-outline-1",
      "polygon": [
        [
          444.691,
          -44.937
        ],
        [
          442.387,
          171.413
        ],
        [
          368.517,
          171.413
        ],
        [
          368.517,
          186.327
        ],
        [
          34.359,
          183.226
        ],
        [
          29.604,
          698.643
        ],
        [
          -106.689,
          696.94
        ],
        [
          -106.689,
          725
        ],
        [
          -307.187,
          725
        ],
        [
          -307.187,
          695.129
        ],
        [
          -445.153,
          693.34
        ],
        [
          -441.213,
          146.74
        ],
        [
          -376.796,
          146.74
        ],
        [
          -375.235,
          -197.129
        ],
        [
          -439.211,
          -198.175
        ],
        [
          -434.731,
          -691.718
        ],
        [
          -294.969,
          -688.39
        ],
        [
          -294.969,
          -725
        ],
        [
          -93.658,
          -725
        ],
        [
          -93.658,
          -686.793
        ],
        [
          42.52,
          -686.793
        ],
        [
          36.888,
          -88.373
        ],
        [
          445.153,
          -85.764
        ]
      ],
      "rawPolygon": [
        [
          54.65533842913122,
          58.87189751389766
        ],
        [
          54.54169939631788,
          48.20231127639749
        ],
        [
          50.89872851173028,
          48.20231127639749
        ],
        [
          50.89872851173028,
          47.46681089659571
        ],
        [
          34.41931338158811,
          47.61974126528536
        ],
        [
          34.18479541538821,
          22.20127641052238
        ],
        [
          27.46333042511058,
          22.28529418302227
        ],
        [
          27.46333042511058,
          20.90146920400344
        ],
        [
          17.57553928963242,
          20.90146920400344
        ],
        [
          17.57553928963242,
          22.37460809664898
        ],
        [
          10.77157808870714,
          22.46284234214303
        ],
        [
          10.96588405900073,
          49.41909514159134
        ],
        [
          14.14265208080285,
          49.41909514159134
        ],
        [
          14.21968201392868,
          66.37744038107635
        ],
        [
          11.06457983889526,
          66.4290044999262
        ],
        [
          11.2855191767947,
          90.7687044793362
        ],
        [
          18.17809810112604,
          90.60455760549766
        ],
        [
          18.17809810112604,
          92.41003878928554
        ],
        [
          28.10599711293866,
          92.41003878928554
        ],
        [
          28.10599711293866,
          90.52579653612916
        ],
        [
          34.82179027929835,
          90.52579653612916
        ],
        [
          34.54400973341478,
          61.01396545007684
        ],
        [
          54.67810740481195,
          60.88530429082654
        ]
      ],
      "closed": true,
      "sourceLayer": "walls",
      "renderAs": "outline",
      "thickness": 0,
      "height": 0,
      "area": 1849.434,
      "autoClosed": false
    }
  ],
  "walls": [],
  "stairs": [
    {
      "id": "floor-3-stair-1",
      "label": "Stair 1",
      "polygon": [
        [
          437.44,
          85.161
        ],
        [
          437.44,
          154.858
        ],
        [
          406.113,
          154.858
        ],
        [
          406.113,
          84.118
        ]
      ],
      "rawPolygon": [
        [
          54.29774843626424,
          52.45593995100877
        ],
        [
          54.29774843626424,
          49.0187524169275
        ],
        [
          52.75281385180725,
          49.0187524169275
        ],
        [
          52.75281385180725,
          52.50738490774342
        ]
      ],
      "position": [
        421.7765,
        119.74875
      ],
      "size": [
        31.326999999999998,
        70.74000000000001
      ],
      "rotation": 0,
      "treads": 8,
      "autoClosed": false
    },
    {
      "id": "floor-3-stair-2",
      "label": "Stair 2",
      "polygon": [
        [
          399.513,
          76.598
        ],
        [
          399.513,
          146.294
        ],
        [
          368.186,
          146.294
        ],
        [
          368.186,
          75.554
        ]
      ],
      "rawPolygon": [
        [
          52.42733756619399,
          52.87824921505682
        ],
        [
          52.42733756619399,
          49.44106168097555
        ],
        [
          50.88240298173699,
          49.44106168097555
        ],
        [
          50.88240298173699,
          52.92969417179147
        ]
      ],
      "position": [
        383.8495,
        111.185
      ],
      "size": [
        31.326999999999998,
        70.74000000000001
      ],
      "rotation": 0,
      "treads": 8,
      "autoClosed": false
    },
    {
      "id": "floor-3-stair-3",
      "label": "Stair 3",
      "polygon": [
        [
          -127.728,
          -686.499
        ],
        [
          -127.728,
          -616.802
        ],
        [
          -151.529,
          -616.802
        ],
        [
          -151.529,
          -687.542
        ]
      ],
      "rawPolygon": [
        [
          26.42578876509351,
          90.51131982335895
        ],
        [
          26.42578876509351,
          87.07413228927769
        ],
        [
          25.25198630011499,
          87.07413228927769
        ],
        [
          25.25198630011499,
          90.56276478009357
        ]
      ],
      "position": [
        -139.6285,
        -651.91125
      ],
      "size": [
        23.801000000000002,
        70.74000000000001
      ],
      "rotation": 0,
      "treads": 8,
      "autoClosed": false
    },
    {
      "id": "floor-3-stair-4",
      "label": "Stair 4",
      "polygon": [
        [
          -99.836,
          -686.381
        ],
        [
          -99.836,
          -625.975
        ],
        [
          -123.637,
          -625.975
        ],
        [
          -123.637,
          -687.424
        ]
      ],
      "rawPolygon": [
        [
          27.80131931018957,
          90.50550335513127
        ],
        [
          27.80131931018957,
          87.5264882170618
        ],
        [
          26.62751684521105,
          87.5264882170618
        ],
        [
          26.62751684521105,
          90.55694831186592
        ]
      ],
      "position": [
        -111.73649999999999,
        -656.43875
      ],
      "size": [
        23.801000000000002,
        61.448999999999955
      ],
      "rotation": 0,
      "treads": 8,
      "autoClosed": false
    },
    {
      "id": "floor-3-stair-5",
      "label": "Stair 5",
      "polygon": [
        [
          -266.58,
          -43.776
        ],
        [
          -352.062,
          -45.678
        ],
        [
          -351.64,
          -86.04
        ],
        [
          -267.688,
          -85.751
        ]
      ],
      "rawPolygon": [
        [
          19.57810332787722,
          58.81462463919472
        ],
        [
          15.36244727228422,
          58.90841836984952
        ],
        [
          15.38328165844902,
          60.89892990621173
        ],
        [
          19.52347376321225,
          60.88464779478848
        ]
      ],
      "position": [
        -309.4925,
        -65.31125
      ],
      "size": [
        85.48200000000003,
        42.264
      ],
      "rotation": 0,
      "treads": 8,
      "autoClosed": false
    },
    {
      "id": "floor-3-stair-6",
      "label": "Stair 6",
      "polygon": [
        [
          -267.867,
          39.83
        ],
        [
          -353.349,
          37.928
        ],
        [
          -352.926,
          -1.006
        ],
        [
          -267.688,
          -0.712
        ],
        [
          -267.867,
          41.258
        ]
      ],
      "rawPolygon": [
        [
          19.51465232224601,
          54.69148102510579
        ],
        [
          15.29899626665301,
          54.78527475576059
        ],
        [
          15.31983065281782,
          56.70536529862437
        ],
        [
          19.52347376321225,
          56.69086430500691
        ],
        [
          19.51465232224601,
          54.62106003160736
        ]
      ],
      "position": [
        -301.9394,
        23.459600000000002
      ],
      "size": [
        85.661,
        42.264
      ],
      "rotation": 0,
      "treads": 8,
      "autoClosed": false
    },
    {
      "id": "floor-3-stair-7",
      "label": "Stair 7",
      "polygon": [
        [
          -112.412,
          633.142
        ],
        [
          -112.412,
          688.903
        ],
        [
          -136.214,
          688.903
        ],
        [
          -136.214,
          632.099
        ]
      ],
      "rawPolygon": [
        [
          27.18109457881226,
          25.43155780244104
        ],
        [
          27.18109457881226,
          22.68163458724774
        ],
        [
          26.00729211383374,
          22.68163458724774
        ],
        [
          26.00729211383374,
          25.48300275917569
        ]
      ],
      "position": [
        -124.313,
        660.76175
      ],
      "size": [
        23.801999999999992,
        56.803999999999974
      ],
      "rotation": 0,
      "treads": 8,
      "autoClosed": false
    },
    {
      "id": "floor-3-stair-8",
      "label": "Stair 8",
      "polygon": [
        [
          -139.561,
          624.191
        ],
        [
          -139.561,
          693.888
        ],
        [
          -161.794,
          693.888
        ],
        [
          -161.794,
          623.148
        ],
        [
          -137.992,
          624.191
        ]
      ],
      "rawPolygon": [
        [
          25.84220365120924,
          25.87298898142947
        ],
        [
          25.84220365120924,
          22.4358014473482
        ],
        [
          24.74577399587763,
          22.4358014473482
        ],
        [
          24.74577399587763,
          25.92443393816412
        ],
        [
          25.91957646085615,
          25.87298898142947
        ]
      ],
      "position": [
        -148.1404,
        651.8612
      ],
      "size": [
        23.80200000000002,
        70.74000000000001
      ],
      "rotation": 0,
      "treads": 8,
      "autoClosed": false
    }
  ],
  "labels": [
    {
      "id": "floor-3-label-3145-1",
      "label": "3145",
      "roomId": "floor-3-3123-47",
      "position": [
        -642.851,
        1148.825
      ],
      "rawPosition": [
        1.021828103683493,
        0
      ],
      "minZoom": 0.64,
      "importance": "normal"
    },
    {
      "id": "floor-3-label-3155-2",
      "label": "3155",
      "roomId": "floor-3-3123-47",
      "position": [
        -663.571,
        1148.825
      ],
      "rawPosition": [
        0,
        1.42e-14
      ],
      "minZoom": 0.64,
      "importance": "normal"
    },
    {
      "id": "floor-3-label-3133-3",
      "label": "3133",
      "roomId": "floor-3-3123-47",
      "position": [
        -642.851,
        1148.825
      ],
      "rawPosition": [
        1.021828103683496,
        0
      ],
      "minZoom": 0.64,
      "importance": "normal"
    },
    {
      "id": "floor-3-label-3145-4",
      "label": "3145",
      "roomId": "floor-3-3145-1",
      "position": [
        -13.963,
        -667.29
      ],
      "rawPosition": [
        32.03625065111728,
        89.5639759188067
      ],
      "minZoom": 0.64,
      "importance": "normal"
    },
    {
      "id": "floor-3-label-3147-5",
      "label": "3147",
      "roomId": "floor-3-3147-2",
      "position": [
        -16.6,
        -574.698
      ],
      "rawPosition": [
        31.90617490965673,
        84.9977040197329
      ],
      "minZoom": 0.64,
      "importance": "normal"
    },
    {
      "id": "floor-3-label-3149-6",
      "label": "3149",
      "roomId": "floor-3-3149-3",
      "position": [
        -16.6,
        -472.711
      ],
      "rawPosition": [
        31.90617490965673,
        79.9680950435052
      ],
      "minZoom": 0.64,
      "importance": "normal"
    },
    {
      "id": "floor-3-label-3151-7",
      "label": "3151",
      "roomId": "floor-3-3151-4",
      "position": [
        -17.514,
        -374.624
      ],
      "rawPosition": [
        31.86111656655293,
        75.13081668964914
      ],
      "minZoom": 0.64,
      "importance": "normal"
    },
    {
      "id": "floor-3-label-3153-8",
      "label": "3153",
      "roomId": "floor-3-3153-5",
      "position": [
        -17.064,
        -277.121
      ],
      "rawPosition": [
        31.88329553132655,
        70.3223229836757
      ],
      "minZoom": 0.64,
      "importance": "normal"
    },
    {
      "id": "floor-3-label-3155-9",
      "label": "3155",
      "roomId": "floor-3-3155-6",
      "position": [
        -50.716,
        -180.966
      ],
      "rawPosition": [
        30.22373265654563,
        65.58033573210697
      ],
      "minZoom": 0.64,
      "importance": "normal"
    },
    {
      "id": "floor-3-label-3157-10",
      "label": "3157",
      "roomId": "floor-3-3157-7",
      "position": [
        -55.483,
        -126.044
      ],
      "rawPosition": [
        29.98861121570087,
        62.87175540991841
      ],
      "minZoom": 0.64,
      "importance": "normal"
    },
    {
      "id": "floor-3-label-3143-11",
      "label": "3143",
      "roomId": "floor-3-3143-8",
      "position": [
        -210.372,
        -698.474
      ],
      "rawPosition": [
        22.35006684288924,
        91.10189277908995
      ],
      "minZoom": 0.64,
      "importance": "normal"
    },
    {
      "id": "floor-3-label-3133-12",
      "label": "3133",
      "roomId": "floor-3-3133-15",
      "position": [
        -244.059,
        -178.766
      ],
      "rawPosition": [
        20.68877923528502,
        65.47182399600028
      ],
      "minZoom": 0.64,
      "importance": "normal"
    },
    {
      "id": "floor-3-label-3135-13",
      "label": "3135",
      "roomId": "floor-3-3135-13",
      "position": [
        -355.466,
        -349.672
      ],
      "rawPosition": [
        15.1945997625839,
        73.90029059134167
      ],
      "minZoom": 0.64,
      "importance": "normal"
    },
    {
      "id": "floor-3-label-3137-14",
      "label": "3137",
      "roomId": "floor-3-3137-12",
      "position": [
        -350.74,
        -475.58
      ],
      "rawPosition": [
        15.42766095236051,
        80.10956676623539
      ],
      "minZoom": 0.64,
      "importance": "normal"
    },
    {
      "id": "floor-3-label-3139-15",
      "label": "3139",
      "roomId": "floor-3-3139-11",
      "position": [
        -350.74,
        -575.859
      ],
      "rawPosition": [
        15.42766095236051,
        85.05495272276121
      ],
      "minZoom": 0.64,
      "importance": "normal"
    },
    {
      "id": "floor-3-label-3141-16",
      "label": "3141",
      "roomId": "floor-3-3141-10",
      "position": [
        -350.74,
        -673.731
      ],
      "rawPosition": [
        15.42766095236051,
        89.88164939597529
      ],
      "minZoom": 0.64,
      "importance": "normal"
    },
    {
      "id": "floor-3-label-3134-17",
      "label": "3134",
      "roomId": "floor-3-3134-9",
      "position": [
        -196.479,
        -313.154
      ],
      "rawPosition": [
        23.03524800339305,
        72.09931212406309
      ],
      "minZoom": 0.64,
      "importance": "normal"
    },
    {
      "id": "floor-3-label-3134a-18",
      "label": "3134A",
      "roomId": "floor-3-3134a-20",
      "position": [
        -196.746,
        -362.983
      ],
      "rawPosition": [
        23.02205832751613,
        74.5567105812314
      ],
      "minZoom": 0.64,
      "importance": "normal"
    },
    {
      "id": "floor-3-label-3142-19",
      "label": "3142",
      "roomId": "floor-3-3142-16",
      "position": [
        -224.804,
        -499.33
      ],
      "rawPosition": [
        21.6383538528272,
        81.28083112749027
      ],
      "minZoom": 0.64,
      "importance": "normal"
    },
    {
      "id": "floor-3-label-3138-20",
      "label": "3138",
      "roomId": "floor-3-3138-18",
      "position": [
        -250.921,
        -402.053
      ],
      "rawPosition": [
        20.35036716806878,
        76.48350431112308
      ],
      "minZoom": 0.64,
      "importance": "normal"
    },
    {
      "id": "floor-3-label-3140-21",
      "label": "3140",
      "roomId": "floor-3-3140-17",
      "position": [
        -250.41,
        -436.25
      ],
      "rawPosition": [
        20.37554106650377,
        78.1699628969283
      ],
      "minZoom": 0.64,
      "importance": "normal"
    },
    {
      "id": "floor-3-label-3131-22",
      "label": "3131",
      "roomId": "floor-3-3131-43",
      "position": [
        -243.853,
        71.784
      ],
      "rawPosition": [
        20.69890247009347,
        53.11561887632643
      ],
      "minZoom": 0.64,
      "importance": "normal"
    },
    {
      "id": "floor-3-label-3129-23",
      "label": "3129",
      "roomId": "floor-3-3129-44",
      "position": [
        -353.088,
        243.293
      ],
      "rawPosition": [
        15.31188537396517,
        44.65745335011181
      ],
      "minZoom": 0.64,
      "importance": "normal"
    },
    {
      "id": "floor-3-label-3127-24",
      "label": "3127",
      "roomId": "floor-3-3127-45",
      "position": [
        -359.103,
        371.658
      ],
      "rawPosition": [
        15.01520772418027,
        38.32695113826553
      ],
      "minZoom": 0.64,
      "importance": "normal"
    },
    {
      "id": "floor-3-label-3125-25",
      "label": "3125",
      "roomId": "floor-3-3125-46",
      "position": [
        -358.444,
        496.871
      ],
      "rawPosition": [
        15.04771128144006,
        32.15195379048731
      ],
      "minZoom": 0.64,
      "importance": "normal"
    },
    {
      "id": "floor-3-label-3123-26",
      "label": "3123",
      "roomId": "floor-3-3123-47",
      "position": [
        -358.439,
        608.891
      ],
      "rawPosition": [
        15.04797906022397,
        26.62753791301885
      ],
      "minZoom": 0.64,
      "importance": "normal"
    },
    {
      "id": "floor-3-label-3121-27",
      "label": "3121",
      "roomId": "floor-3-3121-33",
      "position": [
        -220.688,
        636.71
      ],
      "rawPosition": [
        21.84132874145217,
        25.25561345513398
      ],
      "minZoom": 0.64,
      "importance": "normal"
    },
    {
      "id": "floor-3-label-3116-28",
      "label": "3116",
      "roomId": "floor-3-3116-34",
      "position": [
        -197.783,
        227.178
      ],
      "rawPosition": [
        22.97094375116864,
        45.45218323806669
      ],
      "minZoom": 0.64,
      "importance": "normal"
    },
    {
      "id": "floor-3-label-3116a-29",
      "label": "3116A",
      "roomId": "floor-3-3116a-35",
      "position": [
        -201.409,
        298.166
      ],
      "rawPosition": [
        22.7921009780795,
        41.95133260183114
      ],
      "minZoom": 0.64,
      "importance": "normal"
    },
    {
      "id": "floor-3-label-3130-30",
      "label": "3130",
      "roomId": "floor-3-3130-37",
      "position": [
        -261.164,
        339.897
      ],
      "rawPosition": [
        19.84522179024865,
        39.89332823711426
      ],
      "minZoom": 0.64,
      "importance": "normal"
    },
    {
      "id": "floor-3-label-3128-31",
      "label": "3128",
      "roomId": "floor-3-3128-38",
      "position": [
        -256.905,
        380.257
      ],
      "rawPosition": [
        20.05523485618208,
        37.90292483719111
      ],
      "minZoom": 0.64,
      "importance": "normal"
    },
    {
      "id": "floor-3-label-3126-32",
      "label": "3126",
      "roomId": "floor-3-3126-39",
      "position": [
        -231.916,
        424.156
      ],
      "rawPosition": [
        21.2875986516246,
        35.7379701417346
      ],
      "minZoom": 0.64,
      "importance": "normal"
    },
    {
      "id": "floor-3-label-3113-33",
      "label": "3113",
      "roomId": "floor-3-3113-28",
      "position": [
        -24.411,
        178.755
      ],
      "rawPosition": [
        31.52098425442596,
        47.84024673083624
      ],
      "minZoom": 0.64,
      "importance": "normal"
    },
    {
      "id": "floor-3-label-3115-34",
      "label": "3115",
      "roomId": "floor-3-3115-30",
      "position": [
        -24.522,
        299.441
      ],
      "rawPosition": [
        31.51549942686549,
        41.88843239165275
      ],
      "minZoom": 0.64,
      "importance": "normal"
    },
    {
      "id": "floor-3-label-3117-35",
      "label": "3117",
      "roomId": "floor-3-3117-31",
      "position": [
        -28.126,
        484.498
      ],
      "rawPosition": [
        31.33777958468896,
        32.76214184813369
      ],
      "minZoom": 0.64,
      "importance": "normal"
    },
    {
      "id": "floor-3-label-3115a-36",
      "label": "3115A",
      "roomId": "floor-3-3115-30",
      "position": [
        -47.153,
        416.273
      ],
      "rawPosition": [
        30.39942007271201,
        36.12671639948724
      ],
      "minZoom": 0.64,
      "importance": "normal"
    },
    {
      "id": "floor-3-label-3119-37",
      "label": "3119",
      "roomId": "floor-3-3119-32",
      "position": [
        -27.517,
        615.874
      ],
      "rawPosition": [
        31.36780491662237,
        26.28316830546697
      ],
      "minZoom": 0.64,
      "importance": "normal"
    },
    {
      "id": "floor-3-label-3105-38",
      "label": "3105",
      "roomId": "floor-3-3105-26",
      "position": [
        100.458,
        85.521
      ],
      "rawPosition": [
        37.67904477771836,
        52.43818776429638
      ],
      "minZoom": 0.64,
      "importance": "normal"
    },
    {
      "id": "floor-3-label-3103-39",
      "label": "3103",
      "roomId": "floor-3-3103-25",
      "position": [
        215.51,
        81.471
      ],
      "rawPosition": [
        43.35297382585861,
        52.63791703942159
      ],
      "minZoom": 0.64,
      "importance": "normal"
    },
    {
      "id": "floor-3-label-3101-40",
      "label": "3101",
      "roomId": "floor-3-3101-24",
      "position": [
        321.549,
        82.367
      ],
      "rawPosition": [
        48.58242988553488,
        52.59374563642281
      ],
      "minZoom": 0.64,
      "importance": "normal"
    }
  ],
  "warnings": []
}
